LICENSE
MANIFEST.in
README.md
setup.cfg
setup.py
concur_imgui.egg-info/PKG-INFO
concur_imgui.egg-info/SOURCES.txt
concur_imgui.egg-info/dependency_links.txt
concur_imgui.egg-info/requires.txt
concur_imgui.egg-info/top_level.txt
config-cpp/py_imconfig.cpp
config-cpp/py_imconfig.h
imgui/__init__.py
imgui/_compat.py
imgui/cimgui.pxd
imgui/core.cpp
imgui/core.h
imgui/core.pxd
imgui/core.pyx
imgui/enums.pxd
imgui/extra.py
imgui-cpp/imconfig.h
imgui-cpp/imgui.cpp
imgui-cpp/imgui.h
imgui-cpp/imgui_demo.cpp
imgui-cpp/imgui_draw.cpp
imgui-cpp/imgui_internal.h
imgui-cpp/imgui_widgets.cpp
imgui-cpp/imstb_rectpack.h
imgui-cpp/imstb_textedit.h
imgui-cpp/imstb_truetype.h
imgui-cpp/backends/imgui_impl_allegro5.cpp
imgui-cpp/backends/imgui_impl_allegro5.h
imgui-cpp/backends/imgui_impl_dx10.cpp
imgui-cpp/backends/imgui_impl_dx10.h
imgui-cpp/backends/imgui_impl_dx11.cpp
imgui-cpp/backends/imgui_impl_dx11.h
imgui-cpp/backends/imgui_impl_dx12.cpp
imgui-cpp/backends/imgui_impl_dx12.h
imgui-cpp/backends/imgui_impl_dx9.cpp
imgui-cpp/backends/imgui_impl_dx9.h
imgui-cpp/backends/imgui_impl_glfw.cpp
imgui-cpp/backends/imgui_impl_glfw.h
imgui-cpp/backends/imgui_impl_glut.cpp
imgui-cpp/backends/imgui_impl_glut.h
imgui-cpp/backends/imgui_impl_marmalade.cpp
imgui-cpp/backends/imgui_impl_marmalade.h
imgui-cpp/backends/imgui_impl_metal.h
imgui-cpp/backends/imgui_impl_opengl2.cpp
imgui-cpp/backends/imgui_impl_opengl2.h
imgui-cpp/backends/imgui_impl_opengl3.cpp
imgui-cpp/backends/imgui_impl_opengl3.h
imgui-cpp/backends/imgui_impl_osx.h
imgui-cpp/backends/imgui_impl_sdl.cpp
imgui-cpp/backends/imgui_impl_sdl.h
imgui-cpp/backends/imgui_impl_vulkan.cpp
imgui-cpp/backends/imgui_impl_vulkan.h
imgui-cpp/backends/imgui_impl_win32.cpp
imgui-cpp/backends/imgui_impl_win32.h
imgui-cpp/misc/cpp/imgui_stdlib.cpp
imgui-cpp/misc/cpp/imgui_stdlib.h
imgui-cpp/misc/fonts/binary_to_compressed_c.cpp
imgui-cpp/misc/freetype/imgui_freetype.cpp
imgui-cpp/misc/freetype/imgui_freetype.h
imgui-cpp/misc/single_file/imgui_single_file.h
imgui/integrations/__init__.py
imgui/integrations/cocos2d.py
imgui/integrations/glfw.py
imgui/integrations/opengl.py
imgui/integrations/pygame.py
