Metadata-Version: 2.1
Name: concur-imgui
Version: 1.3.9
Summary: Cython-based Python bindings for dear imgui
Home-page: https://github.com/potocpav/pyimgui
Author: Michał Jaworski
Author-email: swistakm@gmail.com
License: BSD
Platform: UNKNOWN
Classifier: Intended Audience :: Developers
Classifier: License :: OSI Approved :: BSD License
Classifier: Programming Language :: Cython
Classifier: Programming Language :: Python :: 2
Classifier: Programming Language :: Python :: 2.7
Classifier: Programming Language :: Python :: 3
Classifier: Programming Language :: Python :: 3.3
Classifier: Programming Language :: Python :: 3.4
Classifier: Programming Language :: Python :: 3.5
Classifier: Programming Language :: Python :: 3.6
Classifier: Programming Language :: Python :: Implementation :: CPython
Classifier: Programming Language :: Cython
Classifier: Operating System :: MacOS :: MacOS X
Classifier: Operating System :: POSIX :: Linux
Classifier: Operating System :: Microsoft :: Windows
Classifier: Topic :: Games/Entertainment
Provides-Extra: Cython
Provides-Extra: cocos2d
Provides-Extra: full
Provides-Extra: glfw
Provides-Extra: opengl
Provides-Extra: pygame
Provides-Extra: pyglet
Provides-Extra: sdl2
